suite8080/__init__.py
suite8080/asm80.py
suite8080/dis80.py
suite8080-0.5.0.dist-info/LICENSE
suite8080-0.5.0.dist-info/METADATA
suite8080-0.5.0.dist-info/WHEEL
suite8080-0.5.0.dist-info/entry_points.txt
suite8080-0.5.0.dist-info/top_level.txt
suite8080-0.5.0.dist-info/RECORD
