Metadata-Version: 2.1
Name: suite8080
Version: 0.5.0
Summary: Suite of Intel 8080 Assembly tools
Home-page: https://github.com/pamoroso/suite8080
Author: Paolo Amoroso
Author-email: info@paoloamoroso.com
License: MIT
Platform: UNKNOWN
Classifier: Development Status :: 3 - Alpha
Classifier: License :: OSI Approved :: MIT License
Classifier: Programming Language :: Python :: 3
Classifier: Programming Language :: Python :: 3.6
Classifier: Operating System :: OS Independent
Classifier: Environment :: Console
Classifier: Topic :: Software Development
Classifier: Topic :: Software Development :: Assemblers
Classifier: Topic :: Software Development :: Disassemblers
Classifier: Intended Audience :: Developers
Requires-Python: >=3.6
